{
    "arch": "aarch64",
    "build": "hd84c7bf_0",
    "build_number": 0,
    "build_string": "hd84c7bf_0",
    "channel": "https://conda.anaconda.org/conda-forge/linux-aarch64",
    "constrains": [],
    "depends": [
        "libgcc-ng >=12",
        "libstdcxx-ng >=12",
        "libzlib >=1.2.13,<1.3.0a0"
    ],
    "fn": "libsolv-0.7.25-hd84c7bf_0.conda",
    "license": "BSD-3-Clause",
    "license_family": "BSD",
    "md5": "fffab8aa83469b8255767bf4da74d877",
    "name": "libsolv",
    "platform": "linux",
    "sha256": "87f73cbcfdba4a8712ea90b0ed0c213b292013a7219bf9019f15f23bc19d8450",
    "size": 473467,
    "subdir": "linux-aarch64",
    "timestamp": 1695998503214,
    "track_features": "",
    "url": "https://conda.anaconda.org/conda-forge/linux-aarch64/libsolv-0.7.25-hd84c7bf_0.conda",
    "version": "0.7.25"
}